racoons/__init__.py
racoons/data_utils.py
racoons/reporting.py
racoons/visualization.py
racoons/models/__init__.py
racoons/models/classification.py
racoons/models/model_builder.py
racoons/models/validation.py
racoons-0.1.22.dist-info/LICENSE
racoons-0.1.22.dist-info/WHEEL
racoons-0.1.22.dist-info/METADATA
racoons-0.1.22.dist-info/RECORD
