Metadata-Version: 2.1
Name: racoons
Version: 0.1.22
Summary: A package for descriptive analysis of radiological data.
Author-email: Paul-Philipp Jacobs <jacobspaul91@gmail.com>
Requires-Python: >=3.10
Requires-Dist: imblearn==0.0
Requires-Dist: matplotlib==3.8.2
Requires-Dist: numpy==1.26.3
Requires-Dist: openpyxl==3.1.2
Requires-Dist: pandas==2.1.4
Requires-Dist: scikit-learn==1.3.2
Requires-Dist: seaborn==0.13.1
Requires-Dist: tqdm==4.66.1
Requires-Dist: xgboost==2.0.3
Requires-Dist: pytest>=7.4.4 ; extra == "test"
Provides-Extra: test
